{
  "versions": [
    {
      "artifactType": "DATA",
      "version": "v1",
      "publishedAt": null,
      "publishedBy": null,
      "summary": null,
      "priority": "CRITICAL"
    },
    {
      "artifactType": "ASSETS",
      "version": "v1",
      "publishedAt": null,
      "publishedBy": null,
      "summary": null,
      "priority": "STANDARD"
    },
    {
      "artifactType": "APPLICATION",
      "version": "v26",
      "publishedAt": "2026-04-03T14:15:00.000Z",
      "publishedBy": "release",
      "summary": "Flutter client 0.1.12.12 binds the generated offer preview to viewport height so the full snapshot body renders instead of collapsing under the top action bar.",
      "priority": "STANDARD"
    }
  ]
}